<PAMDataset>
  <PAMRasterBand band="1">
    <Description>lsm_1km_dev</Description>
    <Metadata>
      <MDI key="STATISTICS_MAXIMUM">0.80907374620438</MDI>
      <MDI key="STATISTICS_MEAN">-9999</MDI>
      <MDI key="STATISTICS_MINIMUM">0</MDI>
      <MDI key="STATISTICS_STDDEV">-9999</MDI>
    </Metadata>
  </PAMRasterBand>
  <PAMRasterBand band="2">
    <Description>lsm_10km_ed</Description>
    <Metadata>
      <MDI key="STATISTICS_MAXIMUM">471614.34375</MDI>
      <MDI key="STATISTICS_MEAN">-9999</MDI>
      <MDI key="STATISTICS_MINIMUM">217757.84375</MDI>
      <MDI key="STATISTICS_STDDEV">-9999</MDI>
    </Metadata>
  </PAMRasterBand>
  <PAMRasterBand band="3">
    <Description>lsm_10km_dev</Description>
    <Metadata>
      <MDI key="STATISTICS_MAXIMUM">0.15429627895355</MDI>
      <MDI key="STATISTICS_MEAN">-9999</MDI>
      <MDI key="STATISTICS_MINIMUM">0.010959399864078</MDI>
      <MDI key="STATISTICS_STDDEV">-9999</MDI>
    </Metadata>
  </PAMRasterBand>
  <PAMRasterBand band="4">
    <Description>elev_30m</Description>
    <Metadata>
      <MDI key="STATISTICS_MAXIMUM">2418.9755859375</MDI>
      <MDI key="STATISTICS_MEAN">-9999</MDI>
      <MDI key="STATISTICS_MINIMUM">437.38879394531</MDI>
      <MDI key="STATISTICS_STDDEV">-9999</MDI>
    </Metadata>
  </PAMRasterBand>
  <PAMRasterBand band="5">
    <Description>slope_30m</Description>
    <Metadata>
      <MDI key="STATISTICS_MAXIMUM">3.3272042274475</MDI>
      <MDI key="STATISTICS_MEAN">-9999</MDI>
      <MDI key="STATISTICS_MINIMUM">0</MDI>
      <MDI key="STATISTICS_STDDEV">-9999</MDI>
    </Metadata>
  </PAMRasterBand>
  <PAMRasterBand band="6">
    <Description>soil_drainage_30m</Description>
    <Metadata>
      <MDI key="STATISTICS_MAXIMUM">6</MDI>
      <MDI key="STATISTICS_MEAN">-9999</MDI>
      <MDI key="STATISTICS_MINIMUM">0</MDI>
      <MDI key="STATISTICS_STDDEV">-9999</MDI>
    </Metadata>
  </PAMRasterBand>
  <PAMRasterBand band="7">
    <Description>twi_30m</Description>
    <Metadata>
      <MDI key="STATISTICS_MAXIMUM">26.565780639648</MDI>
      <MDI key="STATISTICS_MEAN">-9999</MDI>
      <MDI key="STATISTICS_MINIMUM">2.4846746921539</MDI>
      <MDI key="STATISTICS_STDDEV">-9999</MDI>
    </Metadata>
  </PAMRasterBand>
  <PAMRasterBand band="8">
    <Description>sclass</Description>
    <Metadata>
      <MDI key="STATISTICS_MAXIMUM">180</MDI>
      <MDI key="STATISTICS_MEAN">-9999</MDI>
      <MDI key="STATISTICS_MINIMUM">1</MDI>
      <MDI key="STATISTICS_STDDEV">-9999</MDI>
    </Metadata>
  </PAMRasterBand>
</PAMDataset>
