<PAMDataset>
  <PAMRasterBand band="1">
    <Description>lsm_1km_dev</Description>
    <Metadata>
      <MDI key="STATISTICS_MAXIMUM">0.51795840263367</MDI>
      <MDI key="STATISTICS_MEAN">-9999</MDI>
      <MDI key="STATISTICS_MINIMUM">0</MDI>
      <MDI key="STATISTICS_STDDEV">-9999</MDI>
    </Metadata>
  </PAMRasterBand>
  <PAMRasterBand band="2">
    <Description>lsm_10km_ed</Description>
    <Metadata>
      <MDI key="STATISTICS_MAXIMUM">535291.5</MDI>
      <MDI key="STATISTICS_MEAN">-9999</MDI>
      <MDI key="STATISTICS_MINIMUM">244618.828125</MDI>
      <MDI key="STATISTICS_STDDEV">-9999</MDI>
    </Metadata>
  </PAMRasterBand>
  <PAMRasterBand band="3">
    <Description>lsm_10km_agri</Description>
    <Metadata>
      <MDI key="STATISTICS_MAXIMUM">0.27979651093483</MDI>
      <MDI key="STATISTICS_MEAN">-9999</MDI>
      <MDI key="STATISTICS_MINIMUM">0.044863156974316</MDI>
      <MDI key="STATISTICS_STDDEV">-9999</MDI>
    </Metadata>
  </PAMRasterBand>
  <PAMRasterBand band="4">
    <Description>lsm_10km_dev</Description>
    <Metadata>
      <MDI key="STATISTICS_MAXIMUM">0.058235637843609</MDI>
      <MDI key="STATISTICS_MEAN">-9999</MDI>
      <MDI key="STATISTICS_MINIMUM">0.0029158035758883</MDI>
      <MDI key="STATISTICS_STDDEV">-9999</MDI>
    </Metadata>
  </PAMRasterBand>
  <PAMRasterBand band="5">
    <Description>elev_30m</Description>
    <Metadata>
      <MDI key="STATISTICS_MAXIMUM">2935.5688476562</MDI>
      <MDI key="STATISTICS_MEAN">-9999</MDI>
      <MDI key="STATISTICS_MINIMUM">927.87939453125</MDI>
      <MDI key="STATISTICS_STDDEV">-9999</MDI>
    </Metadata>
  </PAMRasterBand>
  <PAMRasterBand band="6">
    <Description>slope_30m</Description>
    <Metadata>
      <MDI key="STATISTICS_MAXIMUM">3.6458215713501</MDI>
      <MDI key="STATISTICS_MEAN">-9999</MDI>
      <MDI key="STATISTICS_MINIMUM">0</MDI>
      <MDI key="STATISTICS_STDDEV">-9999</MDI>
    </Metadata>
  </PAMRasterBand>
  <PAMRasterBand band="7">
    <Description>soil_drainage_30m</Description>
    <Metadata>
      <MDI key="STATISTICS_MAXIMUM">5</MDI>
      <MDI key="STATISTICS_MEAN">-9999</MDI>
      <MDI key="STATISTICS_MINIMUM">1</MDI>
      <MDI key="STATISTICS_STDDEV">-9999</MDI>
    </Metadata>
  </PAMRasterBand>
  <PAMRasterBand band="8">
    <Description>twi_30m</Description>
    <Metadata>
      <MDI key="STATISTICS_MAXIMUM">24.361083984375</MDI>
      <MDI key="STATISTICS_MEAN">-9999</MDI>
      <MDI key="STATISTICS_MINIMUM">2.5214898586273</MDI>
      <MDI key="STATISTICS_STDDEV">-9999</MDI>
    </Metadata>
  </PAMRasterBand>
  <PAMRasterBand band="9">
    <Description>forest_30m</Description>
    <Metadata>
      <MDI key="STATISTICS_MAXIMUM">1</MDI>
      <MDI key="STATISTICS_MEAN">-9999</MDI>
      <MDI key="STATISTICS_MINIMUM">0</MDI>
      <MDI key="STATISTICS_STDDEV">-9999</MDI>
    </Metadata>
  </PAMRasterBand>
</PAMDataset>
